mountaineer-0.10.1.dist-info/METADATA
mountaineer-0.10.1.dist-info/WHEEL
mountaineer-0.10.1.dist-info/licenses/LICENSE
mountaineer/__init__.py
mountaineer/__tests__/__init__.py
mountaineer/__tests__/actions/__init__.py
mountaineer/__tests__/actions/test_fields.py
mountaineer/__tests__/actions/test_passthrough_dec.py
mountaineer/__tests__/actions/test_sideeffect_dec.py
mountaineer/__tests__/client_builder/__init__.py
mountaineer/__tests__/client_builder/conf_models.py
mountaineer/__tests__/client_builder/file_generators/__init__.py
mountaineer/__tests__/client_builder/file_generators/test_base.py
mountaineer/__tests__/client_builder/file_generators/test_globals.py
mountaineer/__tests__/client_builder/file_generators/test_locals.py
mountaineer/__tests__/client_builder/interface_builders/__init__.py
mountaineer/__tests__/client_builder/interface_builders/common.py
mountaineer/__tests__/client_builder/interface_builders/test_action.py
mountaineer/__tests__/client_builder/interface_builders/test_base.py
mountaineer/__tests__/client_builder/interface_builders/test_controller.py
mountaineer/__tests__/client_builder/interface_builders/test_enum.py
mountaineer/__tests__/client_builder/interface_builders/test_exception.py
mountaineer/__tests__/client_builder/interface_builders/test_model.py
mountaineer/__tests__/client_builder/test_aliases.py
mountaineer/__tests__/client_builder/test_parser.py
mountaineer/__tests__/client_builder/test_types.py
mountaineer/__tests__/client_builder/test_typescript.py
mountaineer/__tests__/client_compiler/__init__.py
mountaineer/__tests__/client_compiler/test_compile.py
mountaineer/__tests__/client_compiler/test_postcss.py
mountaineer/__tests__/client_compiler/test_source_maps.py
mountaineer/__tests__/common.py
mountaineer/__tests__/conftest.py
mountaineer/__tests__/dependencies/__init__.py
mountaineer/__tests__/dependencies/test_base.py
mountaineer/__tests__/development/__init__.py
mountaineer/__tests__/development/conftest.py
mountaineer/__tests__/development/test_message_broker.py
mountaineer/__tests__/development/test_packages.py
mountaineer-0.10.1.dist-info/RECORD
