Metadata-Version: 2.4
Name: mountaineer
Version: 0.10.1
Requires-Dist: pydantic>=2.5.3,<3.0.0
Requires-Dist: fastapi>=0.114.1,<1.0.0
Requires-Dist: inflection>=0.5.1,<1.0.0
Requires-Dist: click>=8.1.7,<9.0.0
Requires-Dist: uvicorn[standard]>=0.27.0.post1,<1.0.0
Requires-Dist: packaging>=23.2
Requires-Dist: pydantic-settings>=2.1.0,<3.0.0
Requires-Dist: websockets<14.0
Requires-Dist: rich>=13.7.1,<14.0.0
Requires-Dist: watchfiles>=1.0.0,<2.0.0
Requires-Dist: firehot>=0.4.0,<1.0.0
Requires-Dist: mountaineer-exceptions>=0.1.1
License-File: LICENSE
Summary: Mountaineer is a batteries-included webapp framework for Python.
Author-email: Pierce Freeman <pierce@freeman.vc>
Requires-Python: >=3.10
